LICENSE.md
MANIFEST.in
README.md
pyproject.toml
setup.cfg
setup.py
data/test/data.db
data/test/geojsons.zip
data/test/test_geojson_no_position/PicAbi_KA09_T112.geojson
data/test/test_geojson_no_position/PseMen_BR07_04.geojson
data/test/test_geojsons/AcePse_SP02_06.geojson
data/test/test_geojsons/FagSyl_BR05_P2T14.geojson
data/test/test_geojsons/PicAbi_KA09_T112.geojson
data/test/test_geojsons/PinSyl_BR05_04.geojson
data/test/test_geojsons/PseMen_BR07_04.geojson
data/test/test_geojsons/QueRub_KA11_P18Tree60.geojson
pytreedb/__init__.py
pytreedb/_types.py
pytreedb/db.py
pytreedb/db_conf.py
pytreedb/db_utils.py
pytreedb.egg-info/PKG-INFO
pytreedb.egg-info/SOURCES.txt
pytreedb.egg-info/dependency_links.txt
pytreedb.egg-info/requires.txt
pytreedb.egg-info/top_level.txt
pytreedb/test/__init__.py
pytreedb/test/test_db.py